{
  "slug": "parc-grands-jardins-charlevoix",
  "title": "Parc national des Grands-Jardins — Charlevoix, Québec",
  "description": "Le Parc national des Grands-Jardins à Charlevoix. Randonnée, raquette, paysages de taïga, caribous et sommets spectaculaires. Géré par la Sépaq.",
  "ogTitle": "Parc national des Grands-Jardins — Charlevoix",
  "ogDescription": "Randonnée, raquette et paysages de taïga au cœur de Charlevoix. Sépaq.",
  "heroGradient": "linear-gradient(135deg, #2D5016 0%, #1a4a2e 100%)",
  "accentColor": "#2D5016",
  "badge": null,
  "heroLocation": "Charlevoix · Québec · Sépaq",
  "h1": "Parc national des<br>Grands-Jardins",
  "tagline": "Des paysages de taïga uniques au sud du 50e parallèle",
  "heroSub": null,
  "backLink": {
    "text": "← Auberge de nos Aïeux",
    "href": "auberge-de-nos-aieux-charlevoix.html"
  },
  "pageType": "guide",
  "quickFacts": [
    {
      "icon": "🏔️",
      "value": "Parc national",
      "label": "Type"
    },
    {
      "icon": "🌲",
      "value": "Taïga boréale",
      "label": "Écosystème"
    },
    {
      "icon": "🥾",
      "value": "Randonnée",
      "label": "Activité phare"
    },
    {
      "icon": "📅",
      "value": "4 saisons",
      "label": "Ouverture"
    }
  ],
  "heroCta": {
    "text": "Planifier ma visite →",
    "href": "https://www.sepaq.com/pq/grj/",
    "external": true
  },
  "sections": [
    {
      "title": "Le parc",
      "paragraphs": [
        "Le Parc national des Grands-Jardins est un joyau naturel de Charlevoix, géré par la Sépaq. C'est l'un des rares endroits au sud du 50e parallèle où l'on retrouve un paysage de taïga boréale — des sommets dénudés, des forêts d'épinettes noires et une végétation qu'on associe normalement au Grand Nord.",
        "Le parc fait partie de la Réserve mondiale de la biosphère de Charlevoix (UNESCO). C'est un terrain de jeu exceptionnel pour les randonneurs, raquetteurs et amoureux de la nature qui cherchent des paysages à couper le souffle sans monter jusqu'au Nunavik."
      ]
    },
    {
      "title": "Activités",
      "highlightCards": [
        {
          "icon": "🥾",
          "title": "Randonnée pédestre",
          "description": "Plusieurs sentiers de différents niveaux. Le Mont du Lac des Cygnes offre un panorama spectaculaire sur la région — l'un des plus beaux sommets de Charlevoix."
        },
        {
          "icon": "🦌",
          "title": "Observation de la faune",
          "description": "Le parc abrite une population de caribous forestiers — l'une des plus méridionales au monde. Orignal, ours noir et lynx habitent aussi la forêt."
        },
        {
          "icon": "🏕️",
          "title": "Camping et hébergement",
          "description": "Emplacements de camping, chalets et refuges disponibles via la Sépaq. Dormir en pleine nature avec le silence de la forêt boréale."
        },
        {
          "icon": "❄️",
          "title": "Raquette et ski de fond",
          "description": "En hiver, plus de 41 km de sentiers de raquette vous attendent. Le parc se transforme en paradis hivernal sous la neige."
        }
      ]
    },
    {
      "title": "À proximité"
    },
    {
      "title": "Infos pratiques",
      "infoCards": [
        {
          "title": "📍 Accès",
          "content": "Via la Route 381, entre Baie-Saint-Paul et le Saguenay"
        },
        {
          "title": "💰 Tarifs",
          "content": "Droits d'accès Sépaq. Réservation recommandée en haute saison."
        },
        {
          "title": "👥 Idéal pour",
          "content": "Randonneurs, familles, photographes, amoureux de la nature, raquetteurs"
        },
        {
          "title": "🌐 Site web",
          "content": "<a href=\"https://www.sepaq.com/pq/grj/\" target=\"_blank\" rel=\"noopener\">sepaq.com/pq/grj</a>"
        }
      ]
    }
  ],
  "ctaBanner": {
    "title": "Planifier votre visite",
    "text": "Consultez les sentiers, tarifs et disponibilités sur le site de la Sépaq.",
    "links": [
      {
        "text": "Visiter le site →",
        "href": "https://www.sepaq.com/pq/grj/"
      }
    ]
  },
  "footer": "Dernière mise à jour : mars 2026 · <a href=\"auberge-de-nos-aieux-charlevoix.html\">← Auberge de nos Aïeux</a> · <a href=\"top-10-auberges-charlevoix-fr.html\">Top 10</a> · <a href=\"/\">onvatujouerdehors.ca</a>"
}